myer_pim_sdk/__init__.py
myer_pim_sdk/client.py
myer_pim_sdk/exceptions.py
myer_pim_sdk/models/__init__.py
myer_pim_sdk/models/attribute.py
myer_pim_sdk/models/category.py
myer_pim_sdk/models/family.py
myer_pim_sdk/models/media_file.py
myer_pim_sdk/models/product.py
myer_pim_sdk/models/product_model.py
myer_pim_sdk/resources/__init__.py
myer_pim_sdk/resources/association_type.py
myer_pim_sdk/resources/attribute.py
myer_pim_sdk/resources/base.py
myer_pim_sdk/resources/category.py
myer_pim_sdk/resources/family.py
myer_pim_sdk/resources/media_file.py
myer_pim_sdk/resources/product.py
myer_pim_sdk/resources/product_model.py
myer_pim_sdk/resources/system.py
myer_pim_sdk/search/__init__.py
myer_pim_sdk/search/builder.py
myer_pim_sdk/search/filters.py
myer_pim_sdk/search/operators.py
myer_pim_sdk/throttler.py
myer_pim_sdk/utils.py
myer_pim_sdk-0.1.2.dist-info/LICENCE
myer_pim_sdk-0.1.2.dist-info/METADATA
myer_pim_sdk-0.1.2.dist-info/WHEEL
myer_pim_sdk-0.1.2.dist-info/RECORD
