Metadata-Version: 2.3
Name: myer-pim-sdk
Version: 0.1.2
Summary: Python library for simplifying the interaction with Myer's PIM API (Akeneo's Product management API)
License: MIT
Author: DuneRaccoon
Author-email: benjamincsherro@hotmail.com
Requires-Python: >=3.10
Classifier: License :: OSI Approved :: MIT License
Classifier: Programming Language :: Python :: 3
Classifier: Programming Language :: Python :: 3.10
Classifier: Programming Language :: Python :: 3.11
Classifier: Programming Language :: Python :: 3.12
Classifier: Programming Language :: Python :: 3.13
Requires-Dist: httpx (>=0.28.1,<0.29.0)
Requires-Dist: leaky-bucket-py (>=0.1.3,<0.2.0)
Requires-Dist: pydantic (>=2.11.7,<3.0.0)
Project-URL: Repository, https://github.com/DuneRaccoon/myer-pim-sdk.git
Project-URL: Source, https://github.com/DuneRaccoon/myer-pim-sdk
